prompts/__about__.py
prompts/__init__.py
prompts/_getch.py
prompts/_styles.py
prompts/input.py
prompts/integration.py
prompts/prompt.py
prompts/question.py
prompts/radio.py
prompts_py-0.1.1.dist-info/METADATA
prompts_py-0.1.1.dist-info/WHEEL
prompts_py-0.1.1.dist-info/licenses/LICENSE.txt
prompts_py-0.1.1.dist-info/RECORD
