Metadata-Version: 2.3
Name: prompts.py
Version: 0.1.1
Summary: Beautiful prompts for Python.
Project-URL: Documentation, https://github.com/ZeroIntensity/prompts.py#readme
Project-URL: Issues, https://github.com/ZeroIntensity/prompts.py/issues
Project-URL: Source, https://github.com/ZeroIntensity/prompts.py
Author-email: ZeroIntensity <zintensitydev@gmail.com>
License-Expression: MIT
License-File: LICENSE.txt
Classifier: Development Status :: 4 - Beta
Classifier: Programming Language :: Python
Classifier: Programming Language :: Python :: 3.8
Classifier: Programming Language :: Python :: 3.9
Classifier: Programming Language :: Python :: 3.10
Classifier: Programming Language :: Python :: 3.11
Classifier: Programming Language :: Python :: 3.12
Classifier: Programming Language :: Python :: Implementation :: CPython
Classifier: Programming Language :: Python :: Implementation :: PyPy
Requires-Python: >=3.8
Requires-Dist: colorama
Requires-Dist: typing-extensions
Provides-Extra: click
Requires-Dist: click; extra == 'click'
